fakepack/__init__.py
fakepack/fakepack.py
fakepack-0.0.2.dist-info/entry_points.txt
fakepack-0.0.2.dist-info/WHEEL
fakepack-0.0.2.dist-info/METADATA
fakepack-0.0.2.dist-info/RECORD
