Metadata-Version: 2.1
Name: fakepack
Version: 0.0.2
Summary: Fake packaging
Author: zae-park
Author-email: tom941105@gmail.com
Requires-Python: >=3.8,<4.0
Classifier: Programming Language :: Python :: 3
Classifier: Programming Language :: Python :: 3.8
